{
  "Routes": [
    {
      "DownstreamPathTemplate": "/api/v1/user/{everything}",
      "DownstreamScheme": "http",
      "DownstreamHostAndPorts": [
        {
          "Host": "localhost",
          "Port": 5000
        }
      ],
      "UpstreamPathTemplate": "/api/user/{everything}",
      "UpstreamHttpMethod": [ "GET", "POST", "PUT", "DELETE" ],
      "AuthenticationOptions": {
        "AuthenticationProviderKey": "Bearer",
        "AllowedScopes": []
      }
    }
  ],
  "GlobalConfiguration": {
    "BaseUrl": "https://meuservidorubuntu.com.br"
  }
}
